asktable_mcp_server/__init__.py
asktable_mcp_server/at_apis.py
asktable_mcp_server/schemas.py
asktable_mcp_server/server.py
asktable_mcp_server/sse_server.py
asktable_mcp_server/version.py
asktable_mcp_server-0.2.23.dist-info/METADATA
asktable_mcp_server-0.2.23.dist-info/WHEEL
asktable_mcp_server-0.2.23.dist-info/entry_points.txt
asktable_mcp_server-0.2.23.dist-info/licenses/LICENSE
asktable_mcp_server-0.2.23.dist-info/RECORD
