Metadata-Version: 2.4
Name: asktable-mcp-server
Version: 0.2.23
Summary: asktable_mcp_server project
Author-email: chenchengfeng <carlos12014@gmail.com>
License-File: LICENSE
Requires-Python: >=3.10
Requires-Dist: aiohttp>=3.9.0
Requires-Dist: asktable>=5.4.0
Requires-Dist: fastmcp>=2.8.0
